{
  "en": {
    "subjects": [
      "A surreal landscape",
      "A portrait of a friend",
      "A mythical creature",
      "A bustling city street",
      "A quiet forest scene",
      "An abandoned building",
      "A futuristic vehicle",
      "A plate of delicious food",
      "A bouquet of flowers",
      "A self-portrait",
      "A character from your favorite book",
      "A scene from a dream",
      "An animal in a human-like situation",
      "A magical object",
      "A robot with emotions",
      "A view from your window",
      "A collection of your favorite things",
      "A person dancing",
      "A reflection in water",
      "A close-up of an insect",
      "A treehouse",
      "A map to a fantasy land",
      "A monster under the bed",
      "A superhero in action",
      "A villain's lair",
      "A potion bottle",
      "A secret garden",
      "A flying ship",
      "A talking animal",
      "A ghost",
      "A knight in shining armor",
      "A dragon",
      "A mermaid",
      "A unicorn",
      "A fairy",
      "A wizard casting a spell",
      "A witch's cauldron",
      "A haunted house",
      "A treasure chest",
      "A pirate ship",
      "A desert island",
      "A jungle temple",
      "A mountain peak",
      "A waterfall",
      "A coral reef",
      "A volcano erupting",
      "A tornado",
      "A lightning storm",
      "A rainbow",
      "A starry night",
      "A sunrise",
      "A sunset",
      "A full moon",
      "A solar eclipse",
      "A black hole",
      "A galaxy",
      "An alien planet",
      "A spaceship",
      "A time machine",
      "A robot army",
      "A cyborg",
      "A post-apocalyptic city",
      "A utopian society",
      "A dystopian world",
      "A fantasy creature",
      "A steampunk invention",
      "A cyberpunk character",
      "A ninja",
      "A samurai",
      "A viking",
      "A gladiator",
      "A Roman senator",
      "A Greek philosopher",
      "An Egyptian pharaoh",
      "A medieval king",
      "A queen",
      "A prince",
      "A princess",
      "A jester",
      "A minstrel",
      "A blacksmith",
      "An alchemist",
      "A scribe",
      "A monk",
      "A nun",
      "A pilgrim",
      "A merchant",
      "A sailor",
      "A farmer",
      "A shepherd",
      "A hunter",
      "A warrior",
      "A shaman",
      "A witch doctor",
      "A medicine man",
      "A tribal chief",
      "A rain dance",
      "A peace pipe",
      "A totem pole",
      "A cave painting",
      "A hieroglyph"
    ],
    "styles": [
      "watercolor style",
      "pixel art",
      "black and white ink",
      "3D rendering"
    ],
    "extras": [
      "transparent texture",
      "futuristic atmosphere",
      "retro feel",
      "vibrant colors"
    ]
  },
  "ja": {
    "subjects": [
      "シュールな風景",
      "友達の肖像画",
      "神話上の生き物",
      "賑やかな街の通り",
      "静かな森の風景",
      "廃墟",
      "未来的な乗り物",
      "美味しそうな食べ物の皿",
      "花束",
      "自画像",
      "好きな本の登場人物",
      "夢の風景",
      "人間のような状況の動物",
      "魔法の品",
      "感情を持つロボット",
      "窓からの眺め",
      "好きなもののコレクション",
      "踊る人",
      "水に映る反射",
      "昆虫の接写",
      "ツリーハウス",
      "ファンタジーの世界への地図",
      "ベッドの下の怪物",
      "活躍中のスーパーヒーロー",
      "悪役の隠れ家",
      "ポーションの瓶",
      "秘密の花園",
      "空飛ぶ船",
      "話す動物",
      "幽霊",
      "輝く鎧の騎士",
      "ドラゴン",
      "人魚",
      "ユニコーン",
      "妖精",
      "呪文を唱える魔法使い",
      "魔女の大釜",
      "お化け屋敷",
      "宝箱",
      "海賊船",
      "無人島",
      "ジャングルの寺院",
      "山の頂",
      "滝",
      "サンゴ礁",
      "噴火する火山",
      "竜巻",
      "雷雨",
      "虹",
      "星月夜",
      "日の出",
      "日没",
      "満月",
      "日食",
      "ブラックホール",
      "銀河",
      "異星の惑星",
      "宇宙船",
      "タイムマシン",
      "ロボット軍団",
      "サイボーグ",
      "終末後の都市",
      "ユートピア社会",
      "ディストピアの世界",
      "ファンタジーの生き物",
      "スチームパンクの発明品",
      "サイバーパンクのキャラクター",
      "忍者",
      "侍",
      "バイキング",
      "剣闘士",
      "ローマの元老院議員",
      "ギリシャの哲学者",
      "エジプトのファラオ",
      "中世の王",
      "女王",
      "王子",
      "王女",
      "道化師",
      "吟遊詩人",
      "鍛冶屋",
      "錬金術師",
      "書記",
      "修道士",
      "修道女",
      "巡礼者",
      "商人",
      "船乗り",
      "農夫",
      "羊飼い",
      "狩人",
      "戦士",
      "シャーマン",
      "呪術医",
      "祈祷師",
      "部族の長",
      "雨乞いの踊り",
      "平和のパイプ",
      "トーテムポール",
      "洞窟壁画",
      "象形文字"
    ],
    "styles": [
      "水彩画スタイル",
      "ピクセルアート",
      "白黒インク",
      "3Dレンダリング"
    ],
    "extras": [
      "透明な質感",
      "未来的な雰囲気",
      "レトロな感じ",
      "鮮やかな色彩"
    ]
  },
  "kr": {
    "subjects": [
      "초현실적인 풍경",
      "친구의 초상화",
      "신화 속의 생물",
      "붐비는 도시의 거리",
      "조용한 숲의 풍경",
      "버려진 건물",
      "미래적인 탈것",
      "맛있는 음식이 담긴 접시",
      "꽃다발",
      "자화상",
      "좋아하는 책의 등장인물",
      "꿈속의 풍경",
      "인간 같은 상황의 동물",
      "마법의 물건",
      "감정을 가진 로봇",
      "창밖 풍경",
      "좋아하는 것들의 컬렉션",
      "춤추는 사람",
      "물에 비친 모습",
      "곤충의 클로즈업",
      "트리하우스",
      "판타지 세계로 가는 지도",
      "침대 밑의 괴물",
      "활약하는 슈퍼히어로",
      "악당의 소굴",
      "포션 병",
      "비밀의 정원",
      "하늘을 나는 배",
      "말하는 동물",
      "유령",
      "빛나는 갑옷을 입은 기사",
      "용",
      "인어",
      "유니콘",
      "요정",
      "주문을 외우는 마법사",
      "마녀의 솥",
      "유령의 집",
      "보물 상자",
      "해적선",
      "무인도",
      "정글의 사원",
      "산 정상",
      "폭포",
      "산호초",
      "화산 폭발",
      "토네이도",
      "뇌우",
      "무지개",
      "별이 빛나는 밤",
      "일출",
      "일몰",
      "보름달",
      "일식",
      "블랙홀",
      "은하",
      "외계 행성",
      "우주선",
      "타임머신",
      "로봇 군대",
      "사이보그",
      "종말 이후의 도시",
      "유토피아 사회",
      "디스토피아 세계",
      "판타지 생물",
      "스팀펑크 발명품",
      "사이버펑크 캐릭터",
      "닌자",
      "사무라이",
      "바이킹",
      "검투사",
      "로마 원로원 의원",
      "그리스 철학자",
      "이집트 파라오",
      "중세의 왕",
      "여왕",
      "왕자",
      "공주",
      "어릿광대",
      "음유시인",
      "대장장이",
      "연금술사",
      "필경사",
      "수도사",
      "수녀",
      "순례자",
      "상인",
      "선원",
      "농부",
      "양치기",
      "사냥꾼",
      "전사",
      "샤먼",
      "주술사",
      "의술사",
      "부족장",
      "기우제",
      "평화의 파이프",
      "토템폴",
      "동굴 벽화",
      "상형문자"
    ],
    "styles": [
      "watercolor style",
      "pixel art",
      "black and white ink",
      "3D rendering"
    ],
    "extras": [
      "transparent texture",
      "futuristic atmosphere",
      "retro feel",
      "vibrant colors"
    ]
  }
}